fit_tech/__init__.py
fit_tech/__main__.py
fit_tech/app/main.py
fit_tech/app/api/dependencies.py
fit_tech/app/api/routes/auth.py
fit_tech/app/api/routes/exercises.py
fit_tech/app/api/routes/ingredients.py
fit_tech/app/api/routes/recipes.py
fit_tech/app/api/routes/reminders.py
fit_tech/app/api/routes/workouts.py
fit_tech/app/bot/run_bot.py
fit_tech/app/core/config.py
fit_tech/app/core/security.py
fit_tech/app/core/models/__init__.py
fit_tech/app/core/models/base.py
fit_tech/app/core/models/exercise.py
fit_tech/app/core/models/ingredient.py
fit_tech/app/core/models/recipe.py
fit_tech/app/core/models/recipe_ingredient.py
fit_tech/app/core/models/reminder.py
fit_tech/app/core/models/user.py
fit_tech/app/core/models/workout.py
fit_tech/app/core/models/workout_exercise.py
fit_tech/app/core/schemas/recipe.py
fit_tech/app/core/schemas/reminder.py
fit_tech/app/core/schemas/user.py
fit_tech/app/core/schemas/workout.py
fit_tech/app/core/services/base.py
fit_tech/app/core/services/exercise.py
fit_tech/app/core/services/ingredient.py
fit_tech/app/core/services/recipe.py
fit_tech/app/core/services/reminder.py
fit_tech/app/core/services/user.py
fit_tech/app/core/services/workout.py
fit_tech/app/db/seed.py
fit_tech/app/db/session.py
fit_tech/app/db/repositories/base.py
fit_tech/app/db/repositories/exercise.py
fit_tech/app/db/repositories/ingredient.py
fit_tech/app/db/repositories/recipe.py
fit_tech/app/db/repositories/reminder.py
fit_tech/app/db/repositories/user.py
fit_tech/app/db/repositories/workout.py
fit_tech/app/workers/celery_app.py
fit_tech/app/workers/tasks.py
fit_tech-0.2.2.dist-info/METADATA
fit_tech-0.2.2.dist-info/WHEEL
fit_tech-0.2.2.dist-info/top_level.txt
fit_tech-0.2.2.dist-info/RECORD
