Metadata-Version: 2.4
Name: fit-tech
Version: 0.2.2
Summary: ФитТех: тренировки, питание, рецепты.
Author-email: Екатерина Мелешко <meleshko.katia@gmail.com>, Валерий Гайдеек <vgaydeek@gmail.com>, Валерия Гопкало <valgopkalo@mail.ru>
Requires-Python: >=3.7
Requires-Dist: fastapi==0.103.1
Requires-Dist: uvicorn==0.23.2
Requires-Dist: sqlalchemy==2.0.40
Requires-Dist: pydantic>2.0
Requires-Dist: email-validator
Requires-Dist: pydantic-settings==2.0.3
Requires-Dist: python-jose==3.3.0
Requires-Dist: passlib==1.7.4
Requires-Dist: bcrypt==4.0.1
Requires-Dist: python-multipart==0.0.6
Requires-Dist: psycopg2-binary==2.9.7
Requires-Dist: redis==4.6.0
Requires-Dist: celery==5.3.4
Requires-Dist: aiogram>=3.2.0
Requires-Dist: icalendar==5.0.7
Requires-Dist: pytz==2023.3
Requires-Dist: httpx==0.25.0
Requires-Dist: jinja2==3.1.2
Requires-Dist: aiofiles<24.2,>=23.2.1
Requires-Dist: geoalchemy2==0.14.0
Requires-Dist: python-dateutil==2.8.2
Requires-Dist: websockets>=10.0
Requires-Dist: asyncpg==0.30.0
Requires-Dist: requests
Provides-Extra: dev
Requires-Dist: pytest==8.2; extra == "dev"
Requires-Dist: pytest-cov==4.1.0; extra == "dev"
